[
  {
    "name": "TANKER 1000",
    "type": "tanker",
    "flag": "Denmark",
    "lat": 26.051462136790505,
    "lon": 56.987879126120035,
    "speed": 0,
    "heading": 193,
    "destination": "SINGAPORE",
    "status": "anchored",
    "timestamp": "2026-03-24T20:37:58.827Z"
  },
  {
    "name": "CONTAINER 1001",
    "type": "container",
    "flag": "Denmark",
    "lat": 27.15072790684365,
    "lon": 55.52256346961417,
    "speed": 0,
    "heading": 89,
    "destination": "JEBEL ALI",
    "status": "anchored",
    "timestamp": "2026-03-24T20:37:58.827Z"
  },
  {
    "name": "TANKER 1002",
    "type": "tanker",
    "flag": "Denmark",
    "lat": 26.897199375957314,
    "lon": 55.552123037633336,
    "speed": 0,
    "heading": 138,
    "destination": "RAS TANURA",
    "status": "anchored",
    "timestamp": "2026-03-24T20:37:58.827Z"
  },
  {
    "name": "TANKER 1003",
    "type": "tanker",
    "flag": "Marshall Islands",
    "lat": 25.85218024365666,
    "lon": 56.214751012239724,
    "speed": 0,
    "heading": 141,
    "destination": "FUJAIRAH",
    "status": "anchored",
    "timestamp": "2026-03-24T20:37:58.827Z"
  },
  {
    "name": "CARGO 1004",
    "type": "cargo",
    "flag": "Panama",
    "lat": 25.89331387686817,
    "lon": 57.423250015588096,
    "speed": 8.781079122839222,
    "heading": 19,
    "destination": "BANDAR ABBAS",
    "status": "moored",
    "timestamp": "2026-03-24T20:37:58.827Z"
  },
  {
    "name": "CONTAINER 1005",
    "type": "container",
    "flag": "Marshall Islands",
    "lat": 26.53422503786053,
    "lon": 56.907287259177494,
    "speed": 11.52814313690348,
    "heading": 29,
    "destination": "FUJAIRAH",
    "status": "moored",
    "timestamp": "2026-03-24T20:37:58.827Z"
  },
  {
    "name": "CONTAINER 1006",
    "type": "container",
    "flag": "Greece",
    "lat": 25.594282822300165,
    "lon": 56.27853994405418,
    "speed": 0,
    "heading": 187,
    "destination": "ROTTERDAM",
    "status": "anchored",
    "timestamp": "2026-03-24T20:37:58.827Z"
  },
  {
    "name": "CARGO 1007",
    "type": "cargo",
    "flag": "Greece",
    "lat": 25.558313383249494,
    "lon": 56.38028953980704,
    "speed": 0,
    "heading": 8,
    "destination": "RAS TANURA",
    "status": "anchored",
    "timestamp": "2026-03-24T20:37:58.827Z"
  },
  {
    "name": "TANKER 1008",
    "type": "tanker",
    "flag": "Liberia",
    "lat": 26.939918001733115,
    "lon": 56.00854811043716,
    "speed": 15.158149948638743,
    "heading": 87,
    "destination": "DUBAI",
    "status": "underway",
    "timestamp": "2026-03-24T20:37:58.827Z"
  },
  {
    "name": "CONTAINER 1009",
    "type": "container",
    "flag": "Hong Kong",
    "lat": 27.080016849290477,
    "lon": 57.017749406754795,
    "speed": 9.203578122431214,
    "heading": 89,
    "destination": "FUJAIRAH",
    "status": "moored",
    "timestamp": "2026-03-24T20:37:58.827Z"
  },
  {
    "name": "CARGO 1010",
    "type": "cargo",
    "flag": "Marshall Islands",
    "lat": 25.672785152955573,
    "lon": 57.07403260051333,
    "speed": 14.61004168530422,
    "heading": 116,
    "destination": "JEBEL ALI",
    "status": "underway",
    "timestamp": "2026-03-24T20:37:58.827Z"
  },
  {
    "name": "TANKER 1011",
    "type": "tanker",
    "flag": "Denmark",
    "lat": 26.63454663582191,
    "lon": 56.86274702725496,
    "speed": 9.804235541178203,
    "heading": 25,
    "destination": "BANDAR ABBAS",
    "status": "underway",
    "timestamp": "2026-03-24T20:37:58.827Z"
  },
  {
    "name": "TANKER 1012",
    "type": "tanker",
    "flag": "Denmark",
    "lat": 26.481901811164587,
    "lon": 56.61131118374264,
    "speed": 12.24888646101994,
    "heading": 324,
    "destination": "RAS TANURA",
    "status": "underway",
    "timestamp": "2026-03-24T20:37:58.827Z"
  },
  {
    "name": "CARGO 1013",
    "type": "cargo",
    "flag": "Hong Kong",
    "lat": 26.544747343638093,
    "lon": 57.22062376150423,
    "speed": 10.577889638490381,
    "heading": 38,
    "destination": "BANDAR ABBAS",
    "status": "moored",
    "timestamp": "2026-03-24T20:37:58.827Z"
  },
  {
    "name": "CARGO 1014",
    "type": "cargo",
    "flag": "Panama",
    "lat": 25.552618714792754,
    "lon": 57.23448841985465,
    "speed": 11.20411254831687,
    "heading": 350,
    "destination": "RAS TANURA",
    "status": "moored",
    "timestamp": "2026-03-24T20:37:58.827Z"
  },
  {
    "name": "TANKER 1015",
    "type": "tanker",
    "flag": "Singapore",
    "lat": 26.825461618229838,
    "lon": 56.864677484837664,
    "speed": 10.005518285395738,
    "heading": 86,
    "destination": "JEBEL ALI",
    "status": "underway",
    "timestamp": "2026-03-24T20:37:58.827Z"
  },
  {
    "name": "TANKER 1016",
    "type": "tanker",
    "flag": "Liberia",
    "lat": 27.265819590559754,
    "lon": 56.83141901054989,
    "speed": 15.783431897019844,
    "heading": 283,
    "destination": "ROTTERDAM",
    "status": "moored",
    "timestamp": "2026-03-24T20:37:58.827Z"
  }
]