[
  {
    "name": "CONTAINER 1000",
    "type": "container",
    "flag": "Panama",
    "lat": 26.87312124523459,
    "lon": 56.49979389518189,
    "speed": 10.326687321568803,
    "heading": 268,
    "destination": "JEBEL ALI",
    "status": "underway",
    "timestamp": "2026-04-20T23:39:26.618Z"
  },
  {
    "name": "TANKER 1001",
    "type": "tanker",
    "flag": "Greece",
    "lat": 26.10957382068732,
    "lon": 57.27949146102952,
    "speed": 12.690768426161753,
    "heading": 200,
    "destination": "ROTTERDAM",
    "status": "underway",
    "timestamp": "2026-04-20T23:39:26.618Z"
  },
  {
    "name": "CARGO 1002",
    "type": "cargo",
    "flag": "Singapore",
    "lat": 25.58766612216739,
    "lon": 55.61067591276652,
    "speed": 12.942106886148597,
    "heading": 161,
    "destination": "DUBAI",
    "status": "underway",
    "timestamp": "2026-04-20T23:39:26.618Z"
  },
  {
    "name": "CONTAINER 1003",
    "type": "container",
    "flag": "Malta",
    "lat": 26.83852626808882,
    "lon": 56.71899372027359,
    "speed": 0,
    "heading": 251,
    "destination": "BANDAR ABBAS",
    "status": "anchored",
    "timestamp": "2026-04-20T23:39:26.618Z"
  },
  {
    "name": "TANKER 1004",
    "type": "tanker",
    "flag": "Singapore",
    "lat": 25.66879126736914,
    "lon": 55.130978652764384,
    "speed": 0,
    "heading": 94,
    "destination": "FUJAIRAH",
    "status": "anchored",
    "timestamp": "2026-04-20T23:39:26.618Z"
  },
  {
    "name": "CARGO 1005",
    "type": "cargo",
    "flag": "Liberia",
    "lat": 26.82574481307317,
    "lon": 57.26409390277767,
    "speed": 0,
    "heading": 12,
    "destination": "RAS TANURA",
    "status": "anchored",
    "timestamp": "2026-04-20T23:39:26.618Z"
  },
  {
    "name": "CONTAINER 1006",
    "type": "container",
    "flag": "Singapore",
    "lat": 26.511205260947687,
    "lon": 56.02015511533512,
    "speed": 0,
    "heading": 334,
    "destination": "ROTTERDAM",
    "status": "anchored",
    "timestamp": "2026-04-20T23:39:26.618Z"
  },
  {
    "name": "CARGO 1007",
    "type": "cargo",
    "flag": "Liberia",
    "lat": 26.62738153689265,
    "lon": 56.745964589360995,
    "speed": 14.681447950324198,
    "heading": 177,
    "destination": "BANDAR ABBAS",
    "status": "underway",
    "timestamp": "2026-04-20T23:39:26.618Z"
  },
  {
    "name": "CARGO 1008",
    "type": "cargo",
    "flag": "Singapore",
    "lat": 26.46436422716639,
    "lon": 56.5676429865464,
    "speed": 12.261479689404947,
    "heading": 148,
    "destination": "SINGAPORE",
    "status": "underway",
    "timestamp": "2026-04-20T23:39:26.618Z"
  },
  {
    "name": "CONTAINER 1009",
    "type": "container",
    "flag": "Singapore",
    "lat": 26.729862696366745,
    "lon": 57.32901545755669,
    "speed": 15.107911647844997,
    "heading": 355,
    "destination": "FUJAIRAH",
    "status": "moored",
    "timestamp": "2026-04-20T23:39:26.618Z"
  },
  {
    "name": "CARGO 1010",
    "type": "cargo",
    "flag": "Hong Kong",
    "lat": 25.682520052590235,
    "lon": 56.69857655959895,
    "speed": 12.070897314572703,
    "heading": 193,
    "destination": "FUJAIRAH",
    "status": "underway",
    "timestamp": "2026-04-20T23:39:26.618Z"
  },
  {
    "name": "CARGO 1011",
    "type": "cargo",
    "flag": "Greece",
    "lat": 26.52269002095058,
    "lon": 55.44500291396339,
    "speed": 9.541724794128028,
    "heading": 167,
    "destination": "FUJAIRAH",
    "status": "moored",
    "timestamp": "2026-04-20T23:39:26.618Z"
  },
  {
    "name": "CONTAINER 1012",
    "type": "container",
    "flag": "Malta",
    "lat": 25.928661063855422,
    "lon": 56.42538261814691,
    "speed": 9.813752759739257,
    "heading": 335,
    "destination": "BANDAR ABBAS",
    "status": "underway",
    "timestamp": "2026-04-20T23:39:26.618Z"
  },
  {
    "name": "CONTAINER 1013",
    "type": "container",
    "flag": "Hong Kong",
    "lat": 27.00035169655171,
    "lon": 56.58796098400028,
    "speed": 0,
    "heading": 172,
    "destination": "ROTTERDAM",
    "status": "anchored",
    "timestamp": "2026-04-20T23:39:26.618Z"
  },
  {
    "name": "CARGO 1014",
    "type": "cargo",
    "flag": "Panama",
    "lat": 27.357634048849846,
    "lon": 56.37238188892305,
    "speed": 13.510010544631314,
    "heading": 143,
    "destination": "RAS TANURA",
    "status": "underway",
    "timestamp": "2026-04-20T23:39:26.618Z"
  },
  {
    "name": "TANKER 1015",
    "type": "tanker",
    "flag": "Greece",
    "lat": 27.316901251599763,
    "lon": 55.155325932698844,
    "speed": 0,
    "heading": 242,
    "destination": "FUJAIRAH",
    "status": "anchored",
    "timestamp": "2026-04-20T23:39:26.618Z"
  },
  {
    "name": "CARGO 1016",
    "type": "cargo",
    "flag": "Greece",
    "lat": 26.124666475695545,
    "lon": 56.38022077035878,
    "speed": 11.726493137504571,
    "heading": 179,
    "destination": "RAS TANURA",
    "status": "moored",
    "timestamp": "2026-04-20T23:39:26.618Z"
  },
  {
    "name": "CARGO 1017",
    "type": "cargo",
    "flag": "Liberia",
    "lat": 27.002311605042095,
    "lon": 55.41154231444546,
    "speed": 0,
    "heading": 5,
    "destination": "FUJAIRAH",
    "status": "anchored",
    "timestamp": "2026-04-20T23:39:26.618Z"
  },
  {
    "name": "CONTAINER 1018",
    "type": "container",
    "flag": "Denmark",
    "lat": 25.579875489475015,
    "lon": 56.6213876807791,
    "speed": 8.585758918899495,
    "heading": 280,
    "destination": "SINGAPORE",
    "status": "moored",
    "timestamp": "2026-04-20T23:39:26.618Z"
  },
  {
    "name": "TANKER 1019",
    "type": "tanker",
    "flag": "Marshall Islands",
    "lat": 27.00756333382629,
    "lon": 55.07833408659987,
    "speed": 0,
    "heading": 1,
    "destination": "DUBAI",
    "status": "anchored",
    "timestamp": "2026-04-20T23:39:26.618Z"
  }
]