[
  {
    "name": "TANKER 1000",
    "type": "tanker",
    "flag": "Greece",
    "lat": 26.209037798644648,
    "lon": 57.04889659377505,
    "speed": 13.557420949822339,
    "heading": 77,
    "destination": "BANDAR ABBAS",
    "status": "moored",
    "timestamp": "2026-03-20T18:43:13.096Z"
  },
  {
    "name": "CONTAINER 1001",
    "type": "container",
    "flag": "Greece",
    "lat": 26.191258223218803,
    "lon": 56.01278084539093,
    "speed": 9.55020623777833,
    "heading": 274,
    "destination": "ROTTERDAM",
    "status": "moored",
    "timestamp": "2026-03-20T18:43:13.096Z"
  },
  {
    "name": "CARGO 1002",
    "type": "cargo",
    "flag": "Marshall Islands",
    "lat": 26.960316213378903,
    "lon": 57.24329711597966,
    "speed": 10.755351094397028,
    "heading": 115,
    "destination": "SINGAPORE",
    "status": "moored",
    "timestamp": "2026-03-20T18:43:13.096Z"
  },
  {
    "name": "TANKER 1003",
    "type": "tanker",
    "flag": "Panama",
    "lat": 26.18295021921059,
    "lon": 56.47434735398249,
    "speed": 0,
    "heading": 237,
    "destination": "RAS TANURA",
    "status": "anchored",
    "timestamp": "2026-03-20T18:43:13.096Z"
  },
  {
    "name": "CARGO 1004",
    "type": "cargo",
    "flag": "Marshall Islands",
    "lat": 25.774809677648904,
    "lon": 55.04992110654519,
    "speed": 14.437687785157932,
    "heading": 274,
    "destination": "ROTTERDAM",
    "status": "underway",
    "timestamp": "2026-03-20T18:43:13.096Z"
  },
  {
    "name": "TANKER 1005",
    "type": "tanker",
    "flag": "Panama",
    "lat": 27.255795041254334,
    "lon": 57.10088109942916,
    "speed": 12.35430692431434,
    "heading": 170,
    "destination": "SINGAPORE",
    "status": "moored",
    "timestamp": "2026-03-20T18:43:13.096Z"
  },
  {
    "name": "TANKER 1006",
    "type": "tanker",
    "flag": "Singapore",
    "lat": 26.392167227777943,
    "lon": 56.348016445968426,
    "speed": 0,
    "heading": 108,
    "destination": "SINGAPORE",
    "status": "anchored",
    "timestamp": "2026-03-20T18:43:13.096Z"
  },
  {
    "name": "TANKER 1007",
    "type": "tanker",
    "flag": "Denmark",
    "lat": 27.020039215726424,
    "lon": 56.714104294333914,
    "speed": 0,
    "heading": 222,
    "destination": "FUJAIRAH",
    "status": "anchored",
    "timestamp": "2026-03-20T18:43:13.096Z"
  },
  {
    "name": "CARGO 1008",
    "type": "cargo",
    "flag": "Greece",
    "lat": 25.9468095343845,
    "lon": 56.333409285131594,
    "speed": 0,
    "heading": 190,
    "destination": "FUJAIRAH",
    "status": "anchored",
    "timestamp": "2026-03-20T18:43:13.096Z"
  },
  {
    "name": "CARGO 1009",
    "type": "cargo",
    "flag": "Denmark",
    "lat": 27.42264251766045,
    "lon": 55.94509882895162,
    "speed": 9.577970164375342,
    "heading": 168,
    "destination": "SINGAPORE",
    "status": "underway",
    "timestamp": "2026-03-20T18:43:13.096Z"
  },
  {
    "name": "CONTAINER 1010",
    "type": "container",
    "flag": "Liberia",
    "lat": 27.412636869985054,
    "lon": 56.94099903825376,
    "speed": 9.348208521375906,
    "heading": 298,
    "destination": "RAS TANURA",
    "status": "moored",
    "timestamp": "2026-03-20T18:43:13.096Z"
  },
  {
    "name": "CONTAINER 1011",
    "type": "container",
    "flag": "Greece",
    "lat": 26.719350830452854,
    "lon": 55.97251124719121,
    "speed": 9.731600556279256,
    "heading": 5,
    "destination": "DUBAI",
    "status": "underway",
    "timestamp": "2026-03-20T18:43:13.096Z"
  },
  {
    "name": "CARGO 1012",
    "type": "cargo",
    "flag": "Liberia",
    "lat": 26.711886161091137,
    "lon": 56.2663719575066,
    "speed": 15.354500718096869,
    "heading": 53,
    "destination": "JEBEL ALI",
    "status": "underway",
    "timestamp": "2026-03-20T18:43:13.096Z"
  },
  {
    "name": "CARGO 1013",
    "type": "cargo",
    "flag": "Greece",
    "lat": 27.206158453663484,
    "lon": 55.588269342646896,
    "speed": 0,
    "heading": 11,
    "destination": "DUBAI",
    "status": "anchored",
    "timestamp": "2026-03-20T18:43:13.096Z"
  },
  {
    "name": "CARGO 1014",
    "type": "cargo",
    "flag": "Liberia",
    "lat": 27.293470221757318,
    "lon": 55.963510180364835,
    "speed": 0,
    "heading": 6,
    "destination": "FUJAIRAH",
    "status": "anchored",
    "timestamp": "2026-03-20T18:43:13.096Z"
  },
  {
    "name": "TANKER 1015",
    "type": "tanker",
    "flag": "Panama",
    "lat": 26.33283636066031,
    "lon": 57.32664066707611,
    "speed": 0,
    "heading": 317,
    "destination": "SINGAPORE",
    "status": "anchored",
    "timestamp": "2026-03-20T18:43:13.096Z"
  },
  {
    "name": "TANKER 1016",
    "type": "tanker",
    "flag": "Malta",
    "lat": 27.392476720706007,
    "lon": 57.13893947797618,
    "speed": 0,
    "heading": 21,
    "destination": "ROTTERDAM",
    "status": "anchored",
    "timestamp": "2026-03-20T18:43:13.096Z"
  }
]