[
  {
    "name": "TANKER 1000",
    "type": "tanker",
    "flag": "Liberia",
    "lat": 26.153037909310196,
    "lon": 56.12241629404457,
    "speed": 9.127368947181797,
    "heading": 131,
    "destination": "JEBEL ALI",
    "status": "moored",
    "timestamp": "2026-04-05T13:52:35.666Z"
  },
  {
    "name": "TANKER 1001",
    "type": "tanker",
    "flag": "Marshall Islands",
    "lat": 26.04690191377976,
    "lon": 56.09271629395025,
    "speed": 9.849023889039465,
    "heading": 175,
    "destination": "DUBAI",
    "status": "moored",
    "timestamp": "2026-04-05T13:52:35.666Z"
  },
  {
    "name": "TANKER 1002",
    "type": "tanker",
    "flag": "Greece",
    "lat": 26.328442976928255,
    "lon": 55.225713803363156,
    "speed": 0,
    "heading": 117,
    "destination": "DUBAI",
    "status": "anchored",
    "timestamp": "2026-04-05T13:52:35.666Z"
  },
  {
    "name": "CARGO 1003",
    "type": "cargo",
    "flag": "Singapore",
    "lat": 26.2280949315323,
    "lon": 55.16680515946931,
    "speed": 0,
    "heading": 34,
    "destination": "DUBAI",
    "status": "anchored",
    "timestamp": "2026-04-05T13:52:35.666Z"
  },
  {
    "name": "TANKER 1004",
    "type": "tanker",
    "flag": "Malta",
    "lat": 27.14257766842501,
    "lon": 56.66115781483288,
    "speed": 10.733181176062837,
    "heading": 326,
    "destination": "RAS TANURA",
    "status": "underway",
    "timestamp": "2026-04-05T13:52:35.666Z"
  },
  {
    "name": "TANKER 1005",
    "type": "tanker",
    "flag": "Liberia",
    "lat": 25.99006087423345,
    "lon": 55.15223029876438,
    "speed": 0,
    "heading": 355,
    "destination": "JEBEL ALI",
    "status": "anchored",
    "timestamp": "2026-04-05T13:52:35.666Z"
  },
  {
    "name": "CARGO 1006",
    "type": "cargo",
    "flag": "Hong Kong",
    "lat": 27.049246996383967,
    "lon": 55.9035638024902,
    "speed": 0,
    "heading": 151,
    "destination": "ROTTERDAM",
    "status": "anchored",
    "timestamp": "2026-04-05T13:52:35.666Z"
  },
  {
    "name": "CARGO 1007",
    "type": "cargo",
    "flag": "Singapore",
    "lat": 26.386507771834996,
    "lon": 56.675764225058636,
    "speed": 14.79562283897952,
    "heading": 165,
    "destination": "RAS TANURA",
    "status": "underway",
    "timestamp": "2026-04-05T13:52:35.666Z"
  },
  {
    "name": "CARGO 1008",
    "type": "cargo",
    "flag": "Denmark",
    "lat": 25.733975466796313,
    "lon": 56.42473503825661,
    "speed": 11.56117724585177,
    "heading": 144,
    "destination": "BANDAR ABBAS",
    "status": "moored",
    "timestamp": "2026-04-05T13:52:35.666Z"
  },
  {
    "name": "CARGO 1009",
    "type": "cargo",
    "flag": "Hong Kong",
    "lat": 26.960203009259224,
    "lon": 55.1989353317236,
    "speed": 0,
    "heading": 125,
    "destination": "FUJAIRAH",
    "status": "anchored",
    "timestamp": "2026-04-05T13:52:35.666Z"
  },
  {
    "name": "CARGO 1010",
    "type": "cargo",
    "flag": "Malta",
    "lat": 27.344508611906555,
    "lon": 56.50356879814786,
    "speed": 10.096572127089098,
    "heading": 196,
    "destination": "JEBEL ALI",
    "status": "moored",
    "timestamp": "2026-04-05T13:52:35.666Z"
  },
  {
    "name": "CARGO 1011",
    "type": "cargo",
    "flag": "Hong Kong",
    "lat": 27.12488871387593,
    "lon": 56.88796298365996,
    "speed": 0,
    "heading": 128,
    "destination": "DUBAI",
    "status": "anchored",
    "timestamp": "2026-04-05T13:52:35.666Z"
  },
  {
    "name": "TANKER 1012",
    "type": "tanker",
    "flag": "Singapore",
    "lat": 26.10714196558758,
    "lon": 57.46434742994186,
    "speed": 11.150301773576597,
    "heading": 221,
    "destination": "ROTTERDAM",
    "status": "moored",
    "timestamp": "2026-04-05T13:52:35.666Z"
  },
  {
    "name": "CONTAINER 1013",
    "type": "container",
    "flag": "Singapore",
    "lat": 27.483969298990765,
    "lon": 56.696135157716895,
    "speed": 9.457423683234088,
    "heading": 54,
    "destination": "SINGAPORE",
    "status": "moored",
    "timestamp": "2026-04-05T13:52:35.666Z"
  },
  {
    "name": "CARGO 1014",
    "type": "cargo",
    "flag": "Hong Kong",
    "lat": 26.438814867592875,
    "lon": 57.164456893443614,
    "speed": 10.21902073376262,
    "heading": 70,
    "destination": "DUBAI",
    "status": "underway",
    "timestamp": "2026-04-05T13:52:35.666Z"
  },
  {
    "name": "CONTAINER 1015",
    "type": "container",
    "flag": "Denmark",
    "lat": 27.039112691713076,
    "lon": 57.18522813717179,
    "speed": 14.204685078135194,
    "heading": 209,
    "destination": "DUBAI",
    "status": "moored",
    "timestamp": "2026-04-05T13:52:35.666Z"
  },
  {
    "name": "CONTAINER 1016",
    "type": "container",
    "flag": "Greece",
    "lat": 25.506572760671823,
    "lon": 55.84181368110219,
    "speed": 0,
    "heading": 267,
    "destination": "SINGAPORE",
    "status": "anchored",
    "timestamp": "2026-04-05T13:52:35.666Z"
  }
]