[
  {
    "name": "CONTAINER 1000",
    "type": "container",
    "flag": "Liberia",
    "lat": 25.66450959983707,
    "lon": 56.73131303254481,
    "speed": 0,
    "heading": 285,
    "destination": "DUBAI",
    "status": "anchored",
    "timestamp": "2026-04-30T02:38:42.146Z"
  },
  {
    "name": "TANKER 1001",
    "type": "tanker",
    "flag": "Singapore",
    "lat": 25.75795167332359,
    "lon": 55.267997784934515,
    "speed": 10.773344407946308,
    "heading": 82,
    "destination": "FUJAIRAH",
    "status": "moored",
    "timestamp": "2026-04-30T02:38:42.146Z"
  },
  {
    "name": "CARGO 1002",
    "type": "cargo",
    "flag": "Marshall Islands",
    "lat": 26.22334892951963,
    "lon": 55.52333389960421,
    "speed": 0,
    "heading": 197,
    "destination": "DUBAI",
    "status": "anchored",
    "timestamp": "2026-04-30T02:38:42.146Z"
  },
  {
    "name": "CARGO 1003",
    "type": "cargo",
    "flag": "Singapore",
    "lat": 25.84401799456787,
    "lon": 55.36643695260208,
    "speed": 14.029566561789892,
    "heading": 249,
    "destination": "ROTTERDAM",
    "status": "underway",
    "timestamp": "2026-04-30T02:38:42.146Z"
  },
  {
    "name": "CONTAINER 1004",
    "type": "container",
    "flag": "Hong Kong",
    "lat": 27.109337974477008,
    "lon": 56.67115209950658,
    "speed": 14.894256332008508,
    "heading": 220,
    "destination": "FUJAIRAH",
    "status": "moored",
    "timestamp": "2026-04-30T02:38:42.146Z"
  },
  {
    "name": "CONTAINER 1005",
    "type": "container",
    "flag": "Marshall Islands",
    "lat": 26.739319195972012,
    "lon": 56.59882289714863,
    "speed": 10.049498068391493,
    "heading": 274,
    "destination": "FUJAIRAH",
    "status": "moored",
    "timestamp": "2026-04-30T02:38:42.146Z"
  },
  {
    "name": "TANKER 1006",
    "type": "tanker",
    "flag": "Malta",
    "lat": 26.32038584126659,
    "lon": 55.072559930349385,
    "speed": 9.48818612825505,
    "heading": 25,
    "destination": "FUJAIRAH",
    "status": "underway",
    "timestamp": "2026-04-30T02:38:42.146Z"
  },
  {
    "name": "CARGO 1007",
    "type": "cargo",
    "flag": "Liberia",
    "lat": 26.39957377054711,
    "lon": 56.27579771195408,
    "speed": 0,
    "heading": 327,
    "destination": "RAS TANURA",
    "status": "anchored",
    "timestamp": "2026-04-30T02:38:42.146Z"
  },
  {
    "name": "CONTAINER 1008",
    "type": "container",
    "flag": "Malta",
    "lat": 26.757698562494962,
    "lon": 55.86094951977862,
    "speed": 13.820766697037849,
    "heading": 161,
    "destination": "ROTTERDAM",
    "status": "moored",
    "timestamp": "2026-04-30T02:38:42.146Z"
  },
  {
    "name": "CONTAINER 1009",
    "type": "container",
    "flag": "Hong Kong",
    "lat": 26.66286123027941,
    "lon": 55.835318641198135,
    "speed": 0,
    "heading": 239,
    "destination": "JEBEL ALI",
    "status": "anchored",
    "timestamp": "2026-04-30T02:38:42.146Z"
  },
  {
    "name": "TANKER 1010",
    "type": "tanker",
    "flag": "Hong Kong",
    "lat": 26.018466918343613,
    "lon": 57.480942976324016,
    "speed": 14.49891133475803,
    "heading": 139,
    "destination": "ROTTERDAM",
    "status": "underway",
    "timestamp": "2026-04-30T02:38:42.146Z"
  },
  {
    "name": "CARGO 1011",
    "type": "cargo",
    "flag": "Singapore",
    "lat": 25.655798421728832,
    "lon": 55.85173432616369,
    "speed": 0,
    "heading": 219,
    "destination": "ROTTERDAM",
    "status": "anchored",
    "timestamp": "2026-04-30T02:38:42.146Z"
  },
  {
    "name": "CONTAINER 1012",
    "type": "container",
    "flag": "Denmark",
    "lat": 26.971617806327785,
    "lon": 56.711550916004406,
    "speed": 11.612865807520294,
    "heading": 302,
    "destination": "ROTTERDAM",
    "status": "underway",
    "timestamp": "2026-04-30T02:38:42.146Z"
  },
  {
    "name": "CARGO 1013",
    "type": "cargo",
    "flag": "Liberia",
    "lat": 26.236973849898497,
    "lon": 55.78403060725771,
    "speed": 11.022892410492384,
    "heading": 188,
    "destination": "BANDAR ABBAS",
    "status": "underway",
    "timestamp": "2026-04-30T02:38:42.146Z"
  },
  {
    "name": "TANKER 1014",
    "type": "tanker",
    "flag": "Panama",
    "lat": 26.650910551651812,
    "lon": 55.14736519440798,
    "speed": 11.659305488215498,
    "heading": 152,
    "destination": "SINGAPORE",
    "status": "underway",
    "timestamp": "2026-04-30T02:38:42.146Z"
  },
  {
    "name": "CONTAINER 1015",
    "type": "container",
    "flag": "Greece",
    "lat": 26.895666376736912,
    "lon": 56.110518993832805,
    "speed": 12.612021746221885,
    "heading": 274,
    "destination": "BANDAR ABBAS",
    "status": "underway",
    "timestamp": "2026-04-30T02:38:42.146Z"
  }
]