[
  {
    "name": "CARGO 1000",
    "type": "cargo",
    "flag": "Liberia",
    "lat": 27.308521552881658,
    "lon": 55.45344471576509,
    "speed": 9.139082839252124,
    "heading": 39,
    "destination": "JEBEL ALI",
    "status": "moored",
    "timestamp": "2026-03-17T13:04:59.057Z"
  },
  {
    "name": "TANKER 1001",
    "type": "tanker",
    "flag": "Marshall Islands",
    "lat": 27.215131253376157,
    "lon": 57.30228795101791,
    "speed": 0,
    "heading": 102,
    "destination": "SINGAPORE",
    "status": "anchored",
    "timestamp": "2026-03-17T13:04:59.057Z"
  },
  {
    "name": "CARGO 1002",
    "type": "cargo",
    "flag": "Panama",
    "lat": 26.74944526367777,
    "lon": 56.9559148708998,
    "speed": 12.123695210809515,
    "heading": 239,
    "destination": "DUBAI",
    "status": "moored",
    "timestamp": "2026-03-17T13:04:59.057Z"
  },
  {
    "name": "CARGO 1003",
    "type": "cargo",
    "flag": "Greece",
    "lat": 26.362870714197474,
    "lon": 55.041961024227064,
    "speed": 8.521430472243788,
    "heading": 200,
    "destination": "DUBAI",
    "status": "moored",
    "timestamp": "2026-03-17T13:04:59.057Z"
  },
  {
    "name": "CONTAINER 1004",
    "type": "container",
    "flag": "Marshall Islands",
    "lat": 26.43690915756239,
    "lon": 56.01995836662318,
    "speed": 11.58928911862677,
    "heading": 175,
    "destination": "RAS TANURA",
    "status": "moored",
    "timestamp": "2026-03-17T13:04:59.057Z"
  },
  {
    "name": "CARGO 1005",
    "type": "cargo",
    "flag": "Liberia",
    "lat": 27.190148779660984,
    "lon": 55.369173840661674,
    "speed": 14.768781799863214,
    "heading": 139,
    "destination": "RAS TANURA",
    "status": "underway",
    "timestamp": "2026-03-17T13:04:59.057Z"
  },
  {
    "name": "TANKER 1006",
    "type": "tanker",
    "flag": "Singapore",
    "lat": 26.73117676898452,
    "lon": 57.12630693924094,
    "speed": 15.89118168002837,
    "heading": 264,
    "destination": "JEBEL ALI",
    "status": "underway",
    "timestamp": "2026-03-17T13:04:59.057Z"
  },
  {
    "name": "CONTAINER 1007",
    "type": "container",
    "flag": "Denmark",
    "lat": 25.581385081946276,
    "lon": 55.27261017389097,
    "speed": 14.00327283741143,
    "heading": 309,
    "destination": "JEBEL ALI",
    "status": "underway",
    "timestamp": "2026-03-17T13:04:59.057Z"
  },
  {
    "name": "CONTAINER 1008",
    "type": "container",
    "flag": "Panama",
    "lat": 27.108754164618244,
    "lon": 55.139643789210844,
    "speed": 15.586224739981738,
    "heading": 270,
    "destination": "DUBAI",
    "status": "moored",
    "timestamp": "2026-03-17T13:04:59.057Z"
  },
  {
    "name": "CARGO 1009",
    "type": "cargo",
    "flag": "Hong Kong",
    "lat": 26.644528100548538,
    "lon": 55.362675824418545,
    "speed": 12.451726172706913,
    "heading": 170,
    "destination": "JEBEL ALI",
    "status": "moored",
    "timestamp": "2026-03-17T13:04:59.057Z"
  },
  {
    "name": "CARGO 1010",
    "type": "cargo",
    "flag": "Malta",
    "lat": 26.830632454121172,
    "lon": 56.43428921437215,
    "speed": 0,
    "heading": 203,
    "destination": "ROTTERDAM",
    "status": "anchored",
    "timestamp": "2026-03-17T13:04:59.057Z"
  },
  {
    "name": "CARGO 1011",
    "type": "cargo",
    "flag": "Malta",
    "lat": 25.548132631139573,
    "lon": 56.82219041163544,
    "speed": 11.452421019857,
    "heading": 110,
    "destination": "ROTTERDAM",
    "status": "underway",
    "timestamp": "2026-03-17T13:04:59.057Z"
  },
  {
    "name": "CARGO 1012",
    "type": "cargo",
    "flag": "Malta",
    "lat": 26.477928108667342,
    "lon": 55.65456536281165,
    "speed": 0,
    "heading": 186,
    "destination": "JEBEL ALI",
    "status": "anchored",
    "timestamp": "2026-03-17T13:04:59.057Z"
  },
  {
    "name": "CARGO 1013",
    "type": "cargo",
    "flag": "Greece",
    "lat": 25.764260019493946,
    "lon": 55.05410866774321,
    "speed": 10.47964517400364,
    "heading": 51,
    "destination": "FUJAIRAH",
    "status": "underway",
    "timestamp": "2026-03-17T13:04:59.057Z"
  },
  {
    "name": "CARGO 1014",
    "type": "cargo",
    "flag": "Hong Kong",
    "lat": 27.28183278200228,
    "lon": 55.499541858249884,
    "speed": 9.468861550859085,
    "heading": 170,
    "destination": "FUJAIRAH",
    "status": "underway",
    "timestamp": "2026-03-17T13:04:59.057Z"
  }
]