[
  {
    "name": "TANKER 1000",
    "type": "tanker",
    "flag": "Greece",
    "lat": 25.723669210033133,
    "lon": 55.416930192544434,
    "speed": 8.913863342937882,
    "heading": 263,
    "destination": "ROTTERDAM",
    "status": "underway",
    "timestamp": "2026-03-21T18:31:28.152Z"
  },
  {
    "name": "TANKER 1001",
    "type": "tanker",
    "flag": "Denmark",
    "lat": 27.499554613824536,
    "lon": 56.00073262117663,
    "speed": 15.073519214332297,
    "heading": 309,
    "destination": "ROTTERDAM",
    "status": "moored",
    "timestamp": "2026-03-21T18:31:28.152Z"
  },
  {
    "name": "TANKER 1002",
    "type": "tanker",
    "flag": "Hong Kong",
    "lat": 27.232355363492474,
    "lon": 56.078888830405795,
    "speed": 0,
    "heading": 234,
    "destination": "SINGAPORE",
    "status": "anchored",
    "timestamp": "2026-03-21T18:31:28.152Z"
  },
  {
    "name": "CARGO 1003",
    "type": "cargo",
    "flag": "Singapore",
    "lat": 26.326037338647133,
    "lon": 56.89658754111531,
    "speed": 10.657799715213793,
    "heading": 343,
    "destination": "JEBEL ALI",
    "status": "moored",
    "timestamp": "2026-03-21T18:31:28.152Z"
  },
  {
    "name": "CARGO 1004",
    "type": "cargo",
    "flag": "Liberia",
    "lat": 26.989629435861513,
    "lon": 56.097445157909235,
    "speed": 10.599484078155848,
    "heading": 20,
    "destination": "FUJAIRAH",
    "status": "underway",
    "timestamp": "2026-03-21T18:31:28.152Z"
  },
  {
    "name": "CARGO 1005",
    "type": "cargo",
    "flag": "Marshall Islands",
    "lat": 26.368265340972005,
    "lon": 56.828720740017204,
    "speed": 11.49389050778847,
    "heading": 177,
    "destination": "JEBEL ALI",
    "status": "moored",
    "timestamp": "2026-03-21T18:31:28.152Z"
  },
  {
    "name": "CONTAINER 1006",
    "type": "container",
    "flag": "Marshall Islands",
    "lat": 26.627561557177035,
    "lon": 55.079750669012746,
    "speed": 9.435529431661342,
    "heading": 254,
    "destination": "BANDAR ABBAS",
    "status": "underway",
    "timestamp": "2026-03-21T18:31:28.152Z"
  },
  {
    "name": "TANKER 1007",
    "type": "tanker",
    "flag": "Panama",
    "lat": 26.768539270995372,
    "lon": 56.687245091549116,
    "speed": 11.485119227778293,
    "heading": 181,
    "destination": "ROTTERDAM",
    "status": "moored",
    "timestamp": "2026-03-21T18:31:28.152Z"
  },
  {
    "name": "CONTAINER 1008",
    "type": "container",
    "flag": "Malta",
    "lat": 27.271000651326794,
    "lon": 55.3731933412458,
    "speed": 11.650232971791128,
    "heading": 39,
    "destination": "FUJAIRAH",
    "status": "underway",
    "timestamp": "2026-03-21T18:31:28.152Z"
  },
  {
    "name": "CARGO 1009",
    "type": "cargo",
    "flag": "Marshall Islands",
    "lat": 26.606292554961538,
    "lon": 55.80458806214325,
    "speed": 0,
    "heading": 261,
    "destination": "RAS TANURA",
    "status": "anchored",
    "timestamp": "2026-03-21T18:31:28.152Z"
  },
  {
    "name": "CARGO 1010",
    "type": "cargo",
    "flag": "Marshall Islands",
    "lat": 26.91594461410062,
    "lon": 55.05311278607017,
    "speed": 10.822520174547234,
    "heading": 208,
    "destination": "SINGAPORE",
    "status": "moored",
    "timestamp": "2026-03-21T18:31:28.152Z"
  },
  {
    "name": "CARGO 1011",
    "type": "cargo",
    "flag": "Greece",
    "lat": 27.184143640043875,
    "lon": 56.01077050746101,
    "speed": 11.880527303548961,
    "heading": 333,
    "destination": "SINGAPORE",
    "status": "underway",
    "timestamp": "2026-03-21T18:31:28.152Z"
  },
  {
    "name": "CARGO 1012",
    "type": "cargo",
    "flag": "Singapore",
    "lat": 26.876930937595027,
    "lon": 56.207148632041395,
    "speed": 11.035022417977084,
    "heading": 231,
    "destination": "BANDAR ABBAS",
    "status": "underway",
    "timestamp": "2026-03-21T18:31:28.152Z"
  },
  {
    "name": "CARGO 1013",
    "type": "cargo",
    "flag": "Greece",
    "lat": 26.85179991921828,
    "lon": 56.216257652014505,
    "speed": 8.127637705201892,
    "heading": 41,
    "destination": "RAS TANURA",
    "status": "moored",
    "timestamp": "2026-03-21T18:31:28.152Z"
  },
  {
    "name": "CARGO 1014",
    "type": "cargo",
    "flag": "Hong Kong",
    "lat": 27.39972244241451,
    "lon": 57.182037431039014,
    "speed": 9.43496418630796,
    "heading": 207,
    "destination": "BANDAR ABBAS",
    "status": "underway",
    "timestamp": "2026-03-21T18:31:28.152Z"
  },
  {
    "name": "CARGO 1015",
    "type": "cargo",
    "flag": "Marshall Islands",
    "lat": 27.39876061187637,
    "lon": 57.2786352917499,
    "speed": 0,
    "heading": 116,
    "destination": "RAS TANURA",
    "status": "anchored",
    "timestamp": "2026-03-21T18:31:28.152Z"
  },
  {
    "name": "CONTAINER 1016",
    "type": "container",
    "flag": "Hong Kong",
    "lat": 26.69031324766269,
    "lon": 55.50087159350352,
    "speed": 11.54092679302558,
    "heading": 144,
    "destination": "DUBAI",
    "status": "underway",
    "timestamp": "2026-03-21T18:31:28.152Z"
  },
  {
    "name": "CARGO 1017",
    "type": "cargo",
    "flag": "Singapore",
    "lat": 25.8611056445275,
    "lon": 57.449657527252754,
    "speed": 0,
    "heading": 112,
    "destination": "ROTTERDAM",
    "status": "anchored",
    "timestamp": "2026-03-21T18:31:28.152Z"
  },
  {
    "name": "TANKER 1018",
    "type": "tanker",
    "flag": "Malta",
    "lat": 26.125706135828423,
    "lon": 57.476039069791135,
    "speed": 11.13362292145342,
    "heading": 237,
    "destination": "DUBAI",
    "status": "underway",
    "timestamp": "2026-03-21T18:31:28.152Z"
  },
  {
    "name": "CARGO 1019",
    "type": "cargo",
    "flag": "Liberia",
    "lat": 25.522874069110937,
    "lon": 56.33774686692231,
    "speed": 12.40126421591958,
    "heading": 179,
    "destination": "JEBEL ALI",
    "status": "moored",
    "timestamp": "2026-03-21T18:31:28.152Z"
  },
  {
    "name": "TANKER 1020",
    "type": "tanker",
    "flag": "Liberia",
    "lat": 25.772795560078613,
    "lon": 56.605018584990056,
    "speed": 0,
    "heading": 143,
    "destination": "FUJAIRAH",
    "status": "anchored",
    "timestamp": "2026-03-21T18:31:28.152Z"
  }
]